jlq_mcp/__init__.py
jlq_mcp/server.py
jlq_mcp-0.1.2.dist-info/WHEEL
jlq_mcp-0.1.2.dist-info/entry_points.txt
jlq_mcp-0.1.2.dist-info/METADATA
jlq_mcp-0.1.2.dist-info/RECORD
