Metadata-Version: 2.3
Name: jlq-mcp
Version: 0.1.2
Summary: Add your description here
Author: 吉
Author-email: 吉 <jiliangqian@harmonycloud.cn>
Requires-Dist: bs4>=0.0.2
Requires-Dist: dashscope>=1.25.8
Requires-Dist: dotenv>=0.9.9
Requires-Dist: httpx>=0.28.1
Requires-Dist: mcp[cli]>=1.25.0
Requires-Python: >=3.11
